{
  "deviceName": "EXAMY 5",
  "overview": "EXAMY 5 EXAMINATION COUCH, HEIGHT ADJUSTABLE EXAMY 5 is designed to use in physical examination clinics, private clinics, manual therapy centers, ultrasound rooms and hospitals. Two sectional ergonomic design Easy to operate Backrest adjustment with gas spring Motorized backrest adjustment (optional) Electrical height adjustment Hydraulic height adjustment by bilateral foot pedal (optional) Hand remote control Foot control switch (optional) Retractable rolling system fixing floor on 4 rubber caps Epoxy painted steel frame High quality foam with synthetic leather coated Foldable, chrome plated side rails (optional) Breathing space with plug (optional) Paper roll holder (optional) Battery Back-up (optional)",
  "specs": [
    {
      "label": "Length",
      "value": "1900 mm"
    },
    {
      "label": "Width",
      "value": "700 mm"
    },
    {
      "label": "Height Range (electrical)",
      "value": "500 – 880 mm"
    },
    {
      "label": "Height Range (hydraulic)",
      "value": "500 – 950 mm"
    },
    {
      "label": "Castor Diameter",
      "value": "50 mm"
    },
    {
      "label": "Backrest Angle",
      "value": "+85° / -30°"
    },
    {
      "label": "Backrest Dimension",
      "value": "700 x 650 mm"
    },
    {
      "label": "Seat Dimension",
      "value": "700 x 1250 mm"
    },
    {
      "label": "Total Lying Surface",
      "value": "700 x 1900 mm"
    },
    {
      "label": "Safe Working Load",
      "value": "220 kg"
    }
  ],
  "features": [],
  "applications": [],
  "compliance": [],
  "notes": []
}